django_soft_deletion/__init__.py
django_soft_deletion/models.py
django_relative_softdeletion-0.0.2.dist-info/LICENSE
django_relative_softdeletion-0.0.2.dist-info/METADATA
django_relative_softdeletion-0.0.2.dist-info/WHEEL
django_relative_softdeletion-0.0.2.dist-info/top_level.txt
django_relative_softdeletion-0.0.2.dist-info/RECORD
