Metadata-Version: 2.1
Name: django-relative-softdeletion
Version: 0.0.2
Summary: A Django models extension to add soft deletion functionality
Home-page: https://github.com/DesignString/django-relative-soft-deletion
Author: Designstring
Author-email: admin@designstring.com
License: MIT
Platform: UNKNOWN
Classifier: Environment :: Web Environment
Classifier: Framework :: Django
Classifier: Intended Audience :: Developers
Classifier: License :: OSI Approved :: MIT License
Classifier: Operating System :: OS Independent
Classifier: Programming Language :: Python
Classifier: Programming Language :: Python :: 3
Classifier: Programming Language :: Python :: 3 :: Only
Classifier: Programming Language :: Python :: 3.6
Classifier: Programming Language :: Python :: 3.7
Classifier: Programming Language :: Python :: 3.8
